setup.py
pkcs/__init__.py
pkcs/opensslconf.py
pkcs/pkcs.py
pkcs.egg-info/PKG-INFO
pkcs.egg-info/SOURCES.txt
pkcs.egg-info/dependency_links.txt
pkcs.egg-info/entry_points.txt
pkcs.egg-info/top_level.txt