Metadata-Version: 1.0
Name: pkcs
Version: 0.1.1
Summary: pkcs tool set
Home-page: http://yunweipai.com
Author: Mao
Author-email: maoxuepeng@gmail.com
License: Apache License
Keywords: pip,python,pkcs,openssl,x509,certificate,ca,self sign
Platform: any
